lofar_sid/README.md
lofar_sid/__init__.py
lofar_sid/_version.py
lofar_sid/contract.py
lofar_sid/interface/opah/grafana_apiv3_pb2.py
lofar_sid/interface/opah/grafana_apiv3_pb2.pyi
lofar_sid/interface/opah/grafana_apiv3_pb2_grpc.py
lofar_sid/interface/stationcontrol/antenna_pb2.py
lofar_sid/interface/stationcontrol/antenna_pb2.pyi
lofar_sid/interface/stationcontrol/antenna_pb2_grpc.py
lofar_sid/interface/stationcontrol/antennafield_pb2.py
lofar_sid/interface/stationcontrol/antennafield_pb2.pyi
lofar_sid/interface/stationcontrol/antennafield_pb2_grpc.py
lofar_sid/interface/stationcontrol/calibration_pb2.py
lofar_sid/interface/stationcontrol/calibration_pb2.pyi
lofar_sid/interface/stationcontrol/calibration_pb2_grpc.py
lofar_sid/interface/stationcontrol/observation_pb2.py
lofar_sid/interface/stationcontrol/observation_pb2.pyi
lofar_sid/interface/stationcontrol/observation_pb2_grpc.py
lofar_sid/interface/stationcontrol/station_pb2.py
lofar_sid/interface/stationcontrol/station_pb2.pyi
lofar_sid/interface/stationcontrol/station_pb2_grpc.py
lofar_sid/interface/stationcontrol/statistics_pb2.py
lofar_sid/interface/stationcontrol/statistics_pb2.pyi
lofar_sid/interface/stationcontrol/statistics_pb2_grpc.py
lofar_sid-1.2.9.dist-info/licenses/LICENSE
lofar_sid-1.2.9.dist-info/METADATA
lofar_sid-1.2.9.dist-info/WHEEL
lofar_sid-1.2.9.dist-info/top_level.txt
lofar_sid-1.2.9.dist-info/RECORD
