Metadata-Version: 2.4
Name: lofar-sid
Version: 1.2.9
Summary: Software interface description
Home-page: https://git.astron.nl/lofar2.0/sid
License: Apache License 2.0
Classifier: Development Status :: 3 - Alpha
Classifier: Environment :: Plugins
Classifier: Intended Audience :: Developers
Classifier: Intended Audience :: Science/Research
Classifier: Operating System :: OS Independent
Classifier: Programming Language :: Python
Classifier: Programming Language :: Python :: 3
Classifier: Programming Language :: Python :: 3 :: Only
Classifier: Programming Language :: Python :: 3.10
Classifier: Programming Language :: Python :: 3.11
Classifier: Programming Language :: Python :: 3.12
Classifier: Topic :: Software Development :: Libraries
Classifier: Topic :: Scientific/Engineering
Classifier: Topic :: Scientific/Engineering :: Astronomy
Classifier: Topic :: Scientific/Engineering :: Interface Engine/Protocol Translator
Requires-Python: >=3.10
License-File: LICENSE
Requires-Dist: numpy
Requires-Dist: grpcio-tools
Dynamic: license-file
